perfbenchify/__init__.py
perfbenchify/main.py
perfbenchify/prompts.py
perfbenchify-2025.12.21145744.dist-info/METADATA
perfbenchify-2025.12.21145744.dist-info/WHEEL
perfbenchify-2025.12.21145744.dist-info/top_level.txt
perfbenchify-2025.12.21145744.dist-info/RECORD
