Metadata-Version: 2.4
Name: perfbenchify
Version: 2025.12.21145744
Summary: A new package that transforms unstructured text descriptions of software performance benchmarks into standardized, comparable metrics. Users input text descriptions of performance tests, and the packa
Author-email: perfbenchify <hi@eugene.plus>
License: MIT
Project-URL: Homepage, https://github.com/chigwell/perfbenchify
Requires-Python: >=3.9
Requires-Dist: langchain-llm7>=0.0.0
Requires-Dist: llmatch-messages>=0.0.0
Requires-Dist: langchain-core>=0.3.0
